gesture_recognition_tools/__init__.py
gesture_recognition_tools/main.py
gesture_recognition_tools/recognition.py
gesture_recognition_tools/utils/__init__.py
gesture_recognition_tools/utils/action_recognizer.py
gesture_recognition_tools/utils/common.py
gesture_recognition_tools/utils/person_detector.py
gesture_recognition_tools/utils/tracker.py
gesture_recognition_tools-1.0.1.dist-info/METADATA
gesture_recognition_tools-1.0.1.dist-info/WHEEL
gesture_recognition_tools-1.0.1.dist-info/top_level.txt
gesture_recognition_tools-1.0.1.dist-info/RECORD
