Metadata-Version: 2.1
Name: gesture-recognition-tools
Version: 1.0.1
Summary: Packages for simple implementations of Gesture Recognition models.
Home-page: https://github.com/suk-6/gesture-recognition-tools.git
Author: suk-6
Author-email: me@suk.kr
License: MIT
Requires-Python: >=3.6
Requires-Dist: opencv-python
Requires-Dist: openvino
Requires-Dist: openvino-dev
Requires-Dist: scipy
